[
  {
    "full_name": "TanStack/router",
    "stargazers_count": 2504,
    "open_issues_count": 36,
    "forks_count": 119
  },
  {
    "full_name": "digidem/mapeo-mobile",
    "stargazers_count": 83,
    "open_issues_count": 135,
    "forks_count": 13
  },
  {
    "full_name": "digidem/mapeo-desktop",
    "stargazers_count": 234,
    "open_issues_count": 62,
    "forks_count": 35
  },
  {
    "full_name": "TomDoesTech/t3-chat",
    "stargazers_count": 29,
    "open_issues_count": 0,
    "forks_count": 9
  },
  {
    "full_name": "jlengstorf/mapbox-show-user-location",
    "stargazers_count": 4,
    "open_issues_count": 0,
    "forks_count": 0
  },
  {
    "full_name": "t3-oss/create-t3-app",
    "stargazers_count": 8139,
    "open_issues_count": 6,
    "forks_count": 335
  },
  {
    "full_name": "vasanthk/react-bits",
    "stargazers_count": 12630,
    "open_issues_count": 9,
    "forks_count": 830
  },
  {
    "full_name": "open-sauced/hot",
    "stargazers_count": 175,
    "open_issues_count": 31,
    "forks_count": 69
  },
  {
    "full_name": "open-sauced/open-sauced",
    "stargazers_count": 803,
    "open_issues_count": 18,
    "forks_count": 413
  },
  {
    "full_name": "firstcontributions/first-contributions",
    "stargazers_count": 29210,
    "open_issues_count": 393,
    "forks_count": 53066
  },
  {
    "full_name": "hibiken/react-places-autocomplete",
    "stargazers_count": 1339,
    "open_issues_count": 127,
    "forks_count": 384
  },
  {
    "full_name": "Ryankolsen/DjangoWebsite",
    "stargazers_count": 1,
    "open_issues_count": 0,
    "forks_count": 0
  }
]