[
  {
    "full_name": "TanStack/router",
    "stargazers_count": 5333,
    "open_issues_count": 59,
    "forks_count": 304
  },
  {
    "full_name": "digidem/mapeo-mobile",
    "stargazers_count": 90,
    "open_issues_count": 124,
    "forks_count": 16
  },
  {
    "full_name": "digidem/mapeo-desktop",
    "stargazers_count": 250,
    "open_issues_count": 76,
    "forks_count": 33
  },
  {
    "full_name": "TomDoesTech/t3-chat",
    "stargazers_count": 61,
    "open_issues_count": 0,
    "forks_count": 22
  },
  {
    "full_name": "jlengstorf/mapbox-show-user-location",
    "stargazers_count": 4,
    "open_issues_count": 0,
    "forks_count": 0
  },
  {
    "full_name": "t3-oss/create-t3-app",
    "stargazers_count": 21428,
    "open_issues_count": 41,
    "forks_count": 935
  },
  {
    "full_name": "vasanthk/react-bits",
    "stargazers_count": 16071,
    "open_issues_count": 9,
    "forks_count": 1138
  },
  {
    "full_name": "open-sauced/hot",
    "stargazers_count": 366,
    "open_issues_count": 32,
    "forks_count": 117
  },
  {
    "full_name": "open-sauced/open-sauced",
    "stargazers_count": 899,
    "open_issues_count": 0,
    "forks_count": 782
  },
  {
    "full_name": "firstcontributions/first-contributions",
    "stargazers_count": 39320,
    "open_issues_count": 257,
    "forks_count": 68687
  },
  {
    "full_name": "hibiken/react-places-autocomplete",
    "stargazers_count": 1361,
    "open_issues_count": 125,
    "forks_count": 390
  },
  {
    "full_name": "Ryankolsen/DjangoWebsite",
    "stargazers_count": 1,
    "open_issues_count": 0,
    "forks_count": 0
  }
]